.ansible-lint
.pre-commit-config.yaml
.stestr.conf
.yamllint
LICENSE
README.rst
ansible-requirements.txt
ansible-test-env-podman.rc
ansible-test-env.rc
bindep.txt
molecule-requirements.txt
requirements.txt
requirements.yml
role-addition.yml
roles
setup.cfg
setup.py
test-requirements.txt
tox.ini
.config/molecule/config.yml
.config/molecule/config_podman.yml
_skeleton_role_/defaults/main.yml.j2
_skeleton_role_/files/.gitkeep
_skeleton_role_/handlers/main.yml
_skeleton_role_/meta/main.yml.j2
_skeleton_role_/molecule/default/converge.yml.j2
_skeleton_role_/molecule/default/molecule.yml
_skeleton_role_/molecule/default/prepare.yml
_skeleton_role_/tasks/main.yml.j2
_skeleton_role_/vars/main.yml.j2
doc/requirements.txt
doc/build/html/.gitkeep
doc/source/conf.py
doc/source/contributing_roles.rst
doc/source/index.rst
doc/source/installation.rst
doc/source/modules.rst
doc/source/roles.rst
doc/source/standalone-roles-playbooks.rst
doc/source/usage.rst
doc/source/_exts/ansible-autodoc.py
doc/source/contributor/contributing.rst
doc/source/modules/action-package.rst
doc/source/modules/action-tripleo_host_prep.rst
doc/source/modules/modules-ceph_spec.rst
doc/source/modules/modules-ceph_spec_bootstrap.rst
doc/source/modules/modules-container-puppet-config.rst
doc/source/modules/modules-tripleo-container-config-scripts.rst
doc/source/modules/modules-tripleo-container-configs.rst
doc/source/modules/modules-tripleo_baremetal_check_existing.rst
doc/source/modules/modules-tripleo_baremetal_expand_roles.rst
doc/source/modules/modules-tripleo_baremetal_populate_environment.rst
doc/source/modules/modules-tripleo_build_heat_environment.rst
doc/source/modules/modules-tripleo_composable_network.rst
doc/source/modules/modules-tripleo_config_download.rst
doc/source/modules/modules-tripleo_container_image_prepare.rst
doc/source/modules/modules-tripleo_deploy_artifacts.rst
doc/source/modules/modules-tripleo_diff_exec.rst
doc/source/modules/modules-tripleo_fernet_keys_rotate.rst
tripleo_ansible.egg-info/PKG-INFO
tripleo_ansible.egg-info/SOURCES.txt
tripleo_ansible.egg-info/dependency_links.txt
tripleo_ansible.egg-info/not-zip-safe
tripleo_ansible.egg-info/pbr.json
tripleo_ansible.egg-info/requires.txt
tripleo_ansible.egg-info/top_level.txt
