Metadata-Version: 1.1
Name: tripleo-ansible
Version: 6.0.0
Summary: Ansible assets for the TripleO project.
Home-page: https://opendev.org/openstack/tripleo-ansible
Author: OpenStack
Author-email: openstack-discuss@lists.openstack.org
License: UNKNOWN
Platform: UNKNOWN
Classifier: License :: OSI Approved :: Apache Software License
Classifier: Development Status :: 4 - Beta
Classifier: Intended Audience :: Developers
Classifier: Intended Audience :: System Administrators
Classifier: Intended Audience :: Information Technology
Classifier: Topic :: Utilities
